AUTHORS
CHANGELOG
LICENSE
MANIFEST.in
README
setup.py
c5filemanager/__init__.py
c5filemanager/models.py
c5filemanager/settings.py
c5filemanager/urls.py
c5filemanager/views.py
c5filemanager/locale/fr/LC_MESSAGES/django.po
c5filemanager/locale/it/LC_MESSAGES/django.po
c5filemanager/tests/__init__.py
c5filemanager/tests/urls.py
c5filemanager/tests/views.py
django_c5filemanager.egg-info/PKG-INFO
django_c5filemanager.egg-info/SOURCES.txt
django_c5filemanager.egg-info/dependency_links.txt
django_c5filemanager.egg-info/requires.txt
django_c5filemanager.egg-info/top_level.txt
docs/Makefile
docs/available_settings.rst
docs/changelog.rst
docs/ckeditor_integration.rst
docs/conf.py
docs/getting_started.rst
docs/index.rst
docs/licensing.rst