Metadata-Version: 1.1
Name: django-c5filemanager
Version: 0.2
Summary: Django connector for Core Five Filemanager.
Home-page: http://mornie.org/projects/django-c5filemanager/
Author: Daniele Tricoli
Author-email: eriol@mornie.org
License: BSD
Platform: UNKNOWN
Classifier: Development Status :: 4 - Beta
Classifier: Environment :: Web Environment
Classifier: Intended Audience :: Developers
Classifier: License :: OSI Approved :: BSD License
Classifier: Operating System :: OS Independent
Classifier: Programming Language :: Python
Classifier: Programming Language :: Python :: 2.6
Classifier: Programming Language :: Python :: 2.7
Classifier: Framework :: Django
